{
    "picks": [
        {
            "element": 145,
            "position": 1,
            "is_captain": false,
            "is_vice_captain": false,
            "multiplier": 1
        },
        {
            "element": 497,
            "position": 2,
            "is_captain": false,
            "is_vice_captain": false,
            "multiplier": 1
        },
        {
            "element": 439,
            "position": 3,
            "is_captain": false,
            "is_vice_captain": false,
            "multiplier": 1
        },
        {
            "element": 313,
            "position": 4,
            "is_captain": false,
            "is_vice_captain": false,
            "multiplier": 1
        },
        {
            "element": 584,
            "position": 5,
            "is_captain": false,
            "is_vice_captain": false,
            "multiplier": 1
        },
        {
            "element": 25,
            "position": 6,
            "is_captain": false,
            "is_vice_captain": false,
            "multiplier": 1
        },
        {
            "element": 501,
            "position": 7,
            "is_captain": false,
            "is_vice_captain": false,
            "multiplier": 1
        },
        {
            "element": 353,
            "position": 8,
            "is_captain": false,
            "is_vice_captain": false,
            "multiplier": 1
        },
        {
            "element": 226,
            "position": 9,
            "is_captain": false,
            "is_vice_captain": false,
            "multiplier": 1
        },
        {
            "element": 355,
            "position": 10,
            "is_captain": false,
            "is_vice_captain": false,
            "multiplier": 1
        },
        {
            "element": 293,
            "position": 11,
            "is_captain": false,
            "is_vice_captain": false,
            "multiplier": 1
        },
        {
            "element": 275,
            "position": 12,
            "is_captain": false,
            "is_vice_captain": false,
            "multiplier": 1
        },
        {
            "element": 349,
            "position": 13,
            "is_captain": false,
            "is_vice_captain": false,
            "multiplier": 1
        },
        {
            "element": 326,
            "position": 14,
            "is_captain": false,
            "is_vice_captain": false,
            "multiplier": 1
        },
        {
            "element": 210,
            "position": 15,
            "is_captain": false,
            "is_vice_captain": false,
            "multiplier": 1
        }
    ],
    "entry_history": {},
    "subs": []
}